qtl_trading_calendar/__init__.py
qtl_trading_calendar/base.py
qtl_trading_calendar/futures.py
qtl_trading_calendar/stock.py
qtl_trading_calendar/utils.py
qtl_trading_calendar/data/futures.toml
qtl_trading_calendar/data/stock.toml
qtl_trading_calendar-20251105.dist-info/METADATA
qtl_trading_calendar-20251105.dist-info/WHEEL
qtl_trading_calendar-20251105.dist-info/top_level.txt
qtl_trading_calendar-20251105.dist-info/RECORD
