Metadata-Version: 2.4
Name: qtl-trading-calendar
Version: 20251105
Summary: Quantalon Trading Calendar
Requires-Python: >=3.11
